lacosmic/__init__.py
lacosmic/conftest.py
lacosmic/core.py
lacosmic/utils.py
lacosmic/version.py
lacosmic/tests/__init__.py
lacosmic/tests/test_core.py
lacosmic-1.4.0.dist-info/licenses/LICENSE.rst
lacosmic-1.4.0.dist-info/METADATA
lacosmic-1.4.0.dist-info/WHEEL
lacosmic-1.4.0.dist-info/top_level.txt
lacosmic-1.4.0.dist-info/RECORD
