Metadata-Version: 2.4
Name: lacosmic
Version: 1.4.0
Summary: Laplacian Cosmic Ray Identification
Author-email: Larry Bradley <larry.bradley@gmail.com>
License-Expression: BSD-3-Clause
Project-URL: Homepage, https://github.com/larrybradley/lacosmic
Project-URL: Documentation, https://lacosmic.readthedocs.io/en/stable/
Keywords: astronomy,astrophysics,images,cosmic rays,cosmic-ray removal,filtering
Classifier: Intended Audience :: Science/Research
Classifier: Natural Language :: English
Classifier: Operating System :: OS Independent
Classifier: Programming Language :: Python
Classifier: Programming Language :: Python :: 3
Classifier: Topic :: Scientific/Engineering :: Astronomy
Requires-Python: >=3.11
License-File: LICENSE.rst
Requires-Dist: astropy>=6.1
Requires-Dist: numpy>=2.0
Requires-Dist: scipy>=1.13
Provides-Extra: test
Requires-Dist: pytest-astropy>=0.11; extra == "test"
Requires-Dist: tox>=4.24; extra == "test"
Provides-Extra: docs
Requires-Dist: matplotlib>=3.9; extra == "docs"
Requires-Dist: numpydoc>=1.8; extra == "docs"
Requires-Dist: pydata-sphinx-theme>=0.16; extra == "docs"
Requires-Dist: pytest-doctestplus>=1.0; extra == "docs"
Requires-Dist: sphinx>=8.2; extra == "docs"
Requires-Dist: sphinx-astropy[confv2]>=1.9.1; extra == "docs"
Requires-Dist: sphinx-automodapi>=0.18; extra == "docs"
Requires-Dist: sphinx-copybutton>=0.5; extra == "docs"
Provides-Extra: dev
Requires-Dist: lacosmic[docs,test]; extra == "dev"
Requires-Dist: pre-commit>=4.0; extra == "dev"
Dynamic: license-file
